odoo/addons/website_event_snippet_calendar/README.rst
odoo/addons/website_event_snippet_calendar/__init__.py
odoo/addons/website_event_snippet_calendar/__manifest__.py
odoo/addons/website_event_snippet_calendar/controllers/__init__.py
odoo/addons/website_event_snippet_calendar/controllers/main.py
odoo/addons/website_event_snippet_calendar/i18n/de.po
odoo/addons/website_event_snippet_calendar/i18n/es.po
odoo/addons/website_event_snippet_calendar/i18n/website_event_snippet_calendar.pot
odoo/addons/website_event_snippet_calendar/models/__init__.py
odoo/addons/website_event_snippet_calendar/models/event_event.py
odoo/addons/website_event_snippet_calendar/readme/CONTRIBUTORS.rst
odoo/addons/website_event_snippet_calendar/readme/DESCRIPTION.rst
odoo/addons/website_event_snippet_calendar/readme/USAGE.rst
odoo/addons/website_event_snippet_calendar/static/description/icon.png
odoo/addons/website_event_snippet_calendar/static/description/icon.svg
odoo/addons/website_event_snippet_calendar/static/description/index.html
odoo/addons/website_event_snippet_calendar/static/src/css/style.scss
odoo/addons/website_event_snippet_calendar/static/src/js/animation.js
odoo/addons/website_event_snippet_calendar/static/src/js/options.js
odoo/addons/website_event_snippet_calendar/static/src/xml/snippets.xml
odoo/addons/website_event_snippet_calendar/templates/assets.xml
odoo/addons/website_event_snippet_calendar/templates/embed.xml
odoo/addons/website_event_snippet_calendar/templates/snippets.xml
odoo12_addon_website_event_snippet_calendar-12.0.1.1.0.dist-info/METADATA
odoo12_addon_website_event_snippet_calendar-12.0.1.1.0.dist-info/WHEEL
odoo12_addon_website_event_snippet_calendar-12.0.1.1.0.dist-info/top_level.txt
odoo12_addon_website_event_snippet_calendar-12.0.1.1.0.dist-info/RECORD
